xortils/__init__.py
xortils/done.py
xortils/plotting.py
xortils-0.0.3.dist-info/METADATA
xortils-0.0.3.dist-info/WHEEL
xortils-0.0.3.dist-info/licenses/LICENSE
xortils-0.0.3.dist-info/RECORD
